Metadata-Version: 2.1
Name: umap-learn
Version: 0.5.8
Summary: Uniform Manifold Approximation and Projection
Home-page: http://github.com/lmcinnes/umap
Maintainer: Leland McInnes
Maintainer-email: leland.mcinnes@gmail.com
License: BSD
Keywords: dimension reduction t-sne manifold
Classifier: Development Status :: 3 - Alpha
Classifier: Intended Audience :: Science/Research
Classifier: Intended Audience :: Developers
Classifier: License :: OSI Approved
Classifier: Programming Language :: C
Classifier: Programming Language :: Python
Classifier: Topic :: Software Development
Classifier: Topic :: Scientific/Engineering
Classifier: Operating System :: Microsoft :: Windows
Classifier: Operating System :: POSIX
Classifier: Operating System :: Unix
Classifier: Operating System :: MacOS
Classifier: Programming Language :: Python :: 3.9
Classifier: Programming Language :: Python :: 3.10
Classifier: Programming Language :: Python :: 3.11
Classifier: Programming Language :: Python :: 3.12
Provides-Extra: plot
Provides-Extra: parametric_umap
Provides-Extra: tbb
License-File: LICENSE.txt
